CHANGELOG.rst
LICENSE.txt
MANIFEST.in
README.rst
requirements.txt
setup.py
baidupcs/__init__.py
baidupcs/api.py
baidupcs/tools.py
baidupcs.egg-info/PKG-INFO
baidupcs.egg-info/SOURCES.txt
baidupcs.egg-info/dependency_links.txt
baidupcs.egg-info/not-zip-safe
baidupcs.egg-info/requires.txt
baidupcs.egg-info/top_level.txt