Metadata-Version: 1.0
Name: baidupcs
Version: 0.3.2
Summary: 百度个人云存储（PCS）Python SDK
Home-page: https://github.com/mozillazg/baidu-pcs-python-sdk
Author: mozillazg
Author-email: mozillazg101@gmail.com
License: MIT
Download-URL: https://github.com/mozillazg/baidu-pcs-python-sdk
Keywords: 百度网盘,百度云,SDK
Platform: UNKNOWN
Classifier: Development Status :: 5 - Production/Stable
Classifier: Intended Audience :: Developers
Classifier: License :: OSI Approved :: MIT License
Classifier: Operating System :: OS Independent
Classifier: Programming Language :: Python
Classifier: Programming Language :: Python :: 2
Classifier: Programming Language :: Python :: 2.6
Classifier: Programming Language :: Python :: 2.7
Classifier: Programming Language :: Python :: 3
Classifier: Programming Language :: Python :: 3.3
Classifier: Topic :: Utilities
